{
  "build": "pl5321hd8ed1ab_0",
  "build_number": 0,
  "channel": "https://conda.anaconda.org/conda-forge/noarch",
  "constrains": [],
  "depends": [
    "perl >=5.32.1,<6.0a0 *_perl5"
  ],
  "extracted_package_dir": "/home/roles/anaconda3/pkgs/perl-common-sense-3.75-pl5321hd8ed1ab_0",
  "features": "",
  "files": [
    "lib/perl5/5.32/vendor_perl/common/sense.pm",
    "lib/perl5/5.32/vendor_perl/common/sense.pod",
    "man/man3/common::sense.3"
  ],
  "fn": "perl-common-sense-3.75-pl5321hd8ed1ab_0.tar.bz2",
  "license": "GPL-1.0-or-later OR Artistic-1.0-Perl",
  "link": {
    "source": "/home/roles/anaconda3/pkgs/perl-common-sense-3.75-pl5321hd8ed1ab_0",
    "type": 1
  },
  "md5": "ef70dc77e8b10bbb62f5e843b401ef0e",
  "name": "perl-common-sense",
  "noarch": "generic",
  "package_tarball_full_path": "/home/roles/anaconda3/pkgs/perl-common-sense-3.75-pl5321hd8ed1ab_0.tar.bz2",
  "package_type": "noarch_generic",
  "paths_data": {
    "paths": [
      {
        "_path": "lib/perl5/5.32/vendor_perl/common/sense.pm",
        "path_type": "hardlink",
        "sha256": "c566b0da4f1c0caeb026a6f1e94dcdf22130400a3db2e8f4fd8bb2b664ab0b26",
        "sha256_in_prefix": "c566b0da4f1c0caeb026a6f1e94dcdf22130400a3db2e8f4fd8bb2b664ab0b26",
        "size_in_bytes": 517
      },
      {
        "_path": "lib/perl5/5.32/vendor_perl/common/sense.pod",
        "path_type": "hardlink",
        "sha256": "639b184eeb5004de157b949247e5de7df04a8f1437bf11cdd154a5b08729459e",
        "sha256_in_prefix": "639b184eeb5004de157b949247e5de7df04a8f1437bf11cdd154a5b08729459e",
        "size_in_bytes": 15929
      },
      {
        "_path": "man/man3/common::sense.3",
        "path_type": "hardlink",
        "sha256": "e3b0c44298fc1c149afbf4c8996fb92427ae41e4649b934ca495991b7852b855",
        "sha256_in_prefix": "e3b0c44298fc1c149afbf4c8996fb92427ae41e4649b934ca495991b7852b855",
        "size_in_bytes": 0
      }
    ],
    "paths_version": 1
  },
  "requested_spec": "None",
  "sha256": "38ef218e9b9d55b9fbdce6b31cf81bcf6f1b16f21b8e7cb9279b41399522a320",
  "size": 20291,
  "subdir": "noarch",
  "timestamp": 1660429950000,
  "track_features": "",
  "url": "https://conda.anaconda.org/conda-forge/noarch/perl-common-sense-3.75-pl5321hd8ed1ab_0.tar.bz2",
  "version": "3.75"
}